[
{"client_id":"152848","business_name":"Affordable Dentures - Texarkana ","num":"19"},
{"client_id":"156014","business_name":"Affordable Dentures - Charlotte ","num":"10"},
{"client_id":"156024","business_name":"Affordable Dentures - Moyock ","num":"10"},
{"client_id":"156025","business_name":"Affordable Dentures - Chester ","num":"10"},
{"client_id":"156026","business_name":"Affordable Dentures - Rocky Gap ","num":"10"},
{"client_id":"156027","business_name":"Affordable Dentures - Winchester ","num":"10"},
{"client_id":"156063","business_name":"Affordable Dentures - Woodbridge ","num":"10"},
{"client_id":"156064","business_name":"Affordable Dentures - Suffolk ","num":"10"},
{"client_id":"156065","business_name":"Affordable Dentures - Virginia Beach ","num":"10"},
{"client_id":"156068","business_name":"Affordable Dentures - Cookeville ","num":"10"},
{"client_id":"156071","business_name":"Affordable Dentures - Lenoir City ","num":"10"},
{"client_id":"156074","business_name":"Affordable Dentures - Chattanooga ","num":"10"},
{"client_id":"156075","business_name":"Affordable Dentures - Dickson ","num":"10"},
{"client_id":"156076","business_name":"Affordable Dentures - Nashville ","num":"10"},
{"client_id":"156078","business_name":"Affordable Dentures - Memphis ","num":"10"},
{"client_id":"156083","business_name":"Affordable Dentures - Morristown ","num":"10"},
{"client_id":"156086","business_name":"Affordable Dentures - Shelbyville ","num":"10"},
{"client_id":"156088","business_name":"Daily Dentures - Knoxville ","num":"10"},
{"client_id":"156090","business_name":"Daily Dentures - Sevierville ","num":"10"},
{"client_id":"156092","business_name":"Affordable Dentures - Florence, KY ","num":"10"},
{"client_id":"156094","business_name":"Affordable Dentures - Richmond ","num":"10"},
{"client_id":"156095","business_name":"Affordable Dentures - Hillview ","num":"10"},
{"client_id":"156096","business_name":"Affordable Dentures - Morehead ","num":"10"},
{"client_id":"156097","business_name":"Affordable Dentures - Bridgeport ","num":"10"},
{"client_id":"156098","business_name":"Affordable Dentures - Huntsville ","num":"10"},
{"client_id":"156101","business_name":"Affordable Dentures - Montgomery ","num":"10"},
{"client_id":"156106","business_name":"Affordable Dentures - Dothan ","num":"10"},
{"client_id":"156107","business_name":"Affordable Dentures - Florence, AL ","num":"10"},
{"client_id":"156109","business_name":"Affordable Dentures - Tuscaloosa ","num":"10"},
{"client_id":"156113","business_name":"Affordable Dentures - Macon ","num":"10"},
{"client_id":"156116","business_name":"Affordable Dentures - Savannah ","num":"10"},
{"client_id":"156120","business_name":"Affordable Dentures - Albany, GA ","num":"10"},
{"client_id":"156122","business_name":"Affordable Dentures - Lagrange ","num":"10"},
{"client_id":"156125","business_name":"Affordable Dentures - Evansville ","num":"10"},
{"client_id":"156126","business_name":"Affordable Dentures - Terre Haute ","num":"10"},
{"client_id":"156131","business_name":"Affordable Dentures - Fort Wayne ","num":"10"},
{"client_id":"156133","business_name":"Affordable Dentures - Lafayette, IN ","num":"10"},
{"client_id":"156135","business_name":"Affordable Dentures - Lima ","num":"10"},
{"client_id":"156136","business_name":"Affordable Dentures - Middletown ","num":"10"},
{"client_id":"156138","business_name":"Affordable Dentures - Chillicothe ","num":"10"},
{"client_id":"156143","business_name":"Affordable Dentures - Columbus, OH ","num":"10"},
{"client_id":"156144","business_name":"Affordable Dentures - Boardman ","num":"10"},
{"client_id":"156145","business_name":"Affordable Dentures - Toledo ","num":"10"},
{"client_id":"156146","business_name":"Affordable Dentures - Conway ","num":"10"},
{"client_id":"156148","business_name":"Affordable Dentures - Little Rock ","num":"10"},
{"client_id":"156149","business_name":"Affordable Dentures - Independence ","num":"10"},
{"client_id":"156150","business_name":"Affordable Dentures - Columbia, MO ","num":"10"},
{"client_id":"156151","business_name":"Affordable Dentures - St. Joseph ","num":"10"},
{"client_id":"156152","business_name":"Affordable Dentures - Sullivan ","num":"10"},
{"client_id":"156153","business_name":"Affordable Dentures - Austin ","num":"10"},
{"client_id":"156156","business_name":"Affordable Dentures - Beaumont ","num":"10"},
{"client_id":"156157","business_name":"Affordable Dentures - Waco ","num":"10"},
{"client_id":"156159","business_name":"Affordable Dentures - Odessa ","num":"10"},
{"client_id":"156163","business_name":"Affordable Dentures - Amarillo ","num":"10"},
{"client_id":"156164","business_name":"Affordable Dentures - Corpus Christi ","num":"10"},
{"client_id":"156165","business_name":"Affordable Dentures - Tyler ","num":"10"},
{"client_id":"156167","business_name":"Affordable Dentures - Conroe ","num":"10"},
{"client_id":"156168","business_name":"Affordable Dentures - Sugarland ","num":"10"},
{"client_id":"156170","business_name":"Affordable Dentures - Friendswood ","num":"10"},
{"client_id":"156171","business_name":"Affordable Dentures - New Braunfels ","num":"10"},
{"client_id":"156172","business_name":"Affordable Dentures - Jackson, MS ","num":"10"},
{"client_id":"156176","business_name":"Affordable Dentures - Tupelo ","num":"10"},
{"client_id":"156178","business_name":"Affordable Dentures - Meridian ","num":"10"},
{"client_id":"156181","business_name":"Affordable Dentures - Lansing ","num":"10"},
{"client_id":"156184","business_name":"Affordable Dentures - Decatur ","num":"10"},
{"client_id":"156186","business_name":"Affordable Dentures - Moline ","num":"10"},
{"client_id":"156189","business_name":"Affordable Dentures - Litchfield ","num":"10"},
{"client_id":"156191","business_name":"Affordable Dentures - Pensacola ","num":"10"},
{"client_id":"156194","business_name":"Affordable Dentures - Fort Myers ","num":"10"},
{"client_id":"156196","business_name":"Affordable Dentures - Gainesville ","num":"10"},
{"client_id":"156200","business_name":"Affordable Dentures - Tampa ","num":"10"},
{"client_id":"156202","business_name":"Affordable Dentures - Orlando ","num":"10"},
{"client_id":"156204","business_name":"Affordable Dentures - Port St. Lucie ","num":"10"},
{"client_id":"156206","business_name":"Affordable Dentures - West Palm Beach ","num":"10"},
{"client_id":"156209","business_name":"Affordable Dentures - West Melbourne ","num":"10"},
{"client_id":"156211","business_name":"Affordable Dentures - Sarasota ","num":"10"},
{"client_id":"156214","business_name":"Affordable Dentures - Jacksonville ","num":"10"},
{"client_id":"156216","business_name":"Affordable Dentures - Fort Lauderdale ","num":"10"},
{"client_id":"156217","business_name":"Affordable Dentures - Daytona Beach ","num":"10"},
{"client_id":"156218","business_name":"Affordable Dentures - Lakeland ","num":"10"},
{"client_id":"156220","business_name":"Affordable Dentures - Weeki Wachee ","num":"10"},
{"client_id":"156221","business_name":"Affordable Dentures - Panama City ","num":"10"},
{"client_id":"156222","business_name":"Affordable Dentures - Avon Park ","num":"10"},
{"client_id":"156225","business_name":"Affordable Dentures - Burlington, VT ","num":"10"},
{"client_id":"156226","business_name":"Affordable Dentures - Madison ","num":"10"},
{"client_id":"156227","business_name":"Affordable Dentures - Milwaukee ","num":"10"},
{"client_id":"156231","business_name":"Affordable Dentures - Eau Claire ","num":"10"},
{"client_id":"156233","business_name":"Affordable Dentures - Sioux City ","num":"10"},
{"client_id":"156235","business_name":"Affordable Dentures - Cedar Rapids ","num":"10"},
{"client_id":"156237","business_name":"Affordable Dentures - Salisbury ","num":"10"},
{"client_id":"156239","business_name":"Affordable Dentures - Providence ","num":"10"},
{"client_id":"156241","business_name":"Affordable Dentures - Myrtle Beach ","num":"10"},
{"client_id":"156242","business_name":"Affordable Dentures - North Charleston ","num":"10"},
{"client_id":"156244","business_name":"Affordable Dentures - Columbia, SC ","num":"10"},
{"client_id":"156245","business_name":"Affordable Dentures - Rock Hill ","num":"10"},
{"client_id":"156250","business_name":"Affordable Dentures - Spokane ","num":"10"},
{"client_id":"156254","business_name":"Affordable Dentures - Tacoma ","num":"10"},
{"client_id":"156257","business_name":"Affordable Dentures - Burlington, WA ","num":"10"},
{"client_id":"156258","business_name":"Affordable Dentures - Sun City ","num":"10"},
{"client_id":"156260","business_name":"Affordable Dentures - Colorado Springs ","num":"10"},
{"client_id":"156261","business_name":"Affordable Dentures - Wilsonville ","num":"10"},
{"client_id":"156264","business_name":"Affordable Dentures - Riverdale ","num":"10"},
{"client_id":"156265","business_name":"Affordable Dentures - American Fork ","num":"10"},
{"client_id":"156268","business_name":"Affordable Dentures - Tulsa ","num":"10"},
{"client_id":"156269","business_name":"Affordable Dentures - Topeka ","num":"10"},
{"client_id":"156578","business_name":"Affordable Dentures - South Hill (New) ","num":"10"},
{"client_id":"161157","business_name":"Affordable Dentures - Fresno ","num":"14"}
]